.coveragerc
.editorconfig
.gitignore
.gitlab-ci.yml
AUTHORS.rst
CONTRIBUTING.rst
HISTORY.rst
LICENSE
MANIFEST.in
Makefile
README.rst
pyproject.toml
pytest.ini
tox.ini
docs/Makefile
docs/about.rst
docs/authors.rst
docs/conf.py
docs/contributing.rst
docs/development.rst
docs/history.rst
docs/index.rst
docs/installation.rst
docs/make.bat
docs/usage.rst
docs/_build/html/_static/file.png
docs/_build/html/_static/minus.png
docs/_build/html/_static/plus.png
docs/_static/wider_theme.css
docs/images/overview-scheme__900x366.png
sensormapgeo/__init__.py
sensormapgeo/transformer.py
sensormapgeo/transformer_2d.py
sensormapgeo/transformer_3d.py
sensormapgeo/utils.py
sensormapgeo/version.py
sensormapgeo.egg-info/PKG-INFO
sensormapgeo.egg-info/SOURCES.txt
sensormapgeo.egg-info/dependency_links.txt
sensormapgeo.egg-info/not-zip-safe
sensormapgeo.egg-info/requires.txt
sensormapgeo.egg-info/top_level.txt
sensormapgeo/gdal_backend/__init__.py
sensormapgeo/gdal_backend/transformer_2d.py
sensormapgeo/gdal_backend/transformer_3d.py
sensormapgeo/pyresample_backend/__init__.py
sensormapgeo/pyresample_backend/transformer_2d.py
sensormapgeo/pyresample_backend/transformer_3d.py