Metadata-Version: 2.1
Name: sensormapgeo
Version: 1.1.0
Summary: A package for transforming remote sensing images between sensor and map geometry
Author-email: Daniel Scheffler <daniel.scheffler@gfz-potsdam.de>
License: Apache-2.0
Project-URL: Source code, https://git.gfz-potsdam.de/EnMAP/sensormapgeo
Project-URL: Issue Tracker, https://git.gfz-potsdam.de/EnMAP/sensormapgeo/-/issues
Project-URL: Documentation, https://enmap.git-pages.gfz-potsdam.de/sensormapgeo/doc/
Project-URL: Change log, https://enmap.git-pages.gfz-potsdam.de/sensormapgeo/doc/history.html
Keywords: sensormapgeo,geometric pre-processing,remote sensing,orthorectification
Classifier: Development Status :: 5 - Production/Stable
Classifier: Intended Audience :: Science/Research
Classifier: License :: OSI Approved :: Apache Software License
Classifier: Natural Language :: English
Classifier: Programming Language :: Python :: 3
Classifier: Programming Language :: Python :: 3.8
Classifier: Programming Language :: Python :: 3.9
Classifier: Programming Language :: Python :: 3.10
Classifier: Programming Language :: Python :: 3.11
Classifier: Programming Language :: Python :: 3.12
Classifier: Topic :: Scientific/Engineering
Requires-Python: >=3.8
License-File: LICENSE
Requires-Dist: gdal>=3.8
Requires-Dist: joblib
Requires-Dist: numpy
Requires-Dist: py_tools_ds>=0.18.0
Requires-Dist: pyproj>=2.2
Requires-Dist: pyresample>=1.17.0
Provides-Extra: doc
Requires-Dist: sphinx-argparse; extra == "doc"
Requires-Dist: sphinx_rtd_theme; extra == "doc"
Requires-Dist: sphinx-autodoc-typehints; extra == "doc"
Provides-Extra: test
Requires-Dist: pytest; extra == "test"
Requires-Dist: pytest-cov; extra == "test"
Requires-Dist: pytest-reporter-html1; extra == "test"
Requires-Dist: pytest-subtests; extra == "test"
Requires-Dist: urlchecker; extra == "test"
Provides-Extra: lint
Requires-Dist: flake8; extra == "lint"
Requires-Dist: pycodestyle; extra == "lint"
Requires-Dist: pydocstyle; extra == "lint"
Provides-Extra: dev
Requires-Dist: sensormapgeo[test]; extra == "dev"
Requires-Dist: sensormapgeo[doc]; extra == "dev"
Requires-Dist: sensormapgeo[lint]; extra == "dev"
